README.md
setup.cfg
setup.py
eis/__init__.py
eis/accounting/__init__.py
eis/accounting/api_client.py
eis/accounting/configuration.py
eis/accounting/exceptions.py
eis/accounting/model_utils.py
eis/accounting/rest.py
eis/accounting/api/__init__.py
eis/accounting/api/booking_entries_api.py
eis/accounting/api/financial_accounts_api.py
eis/accounting/api/financial_transactions_api.py
eis/accounting/api/health_api.py
eis/accounting/api/number_ranges_api.py
eis/accounting/api/personal_accounts_api.py
eis/accounting/apis/__init__.py
eis/accounting/model/__init__.py
eis/accounting/model/booking_entry_class.py
eis/accounting/model/create_booking_entry_request_dto.py
eis/accounting/model/create_booking_entry_response_class.py
eis/accounting/model/create_financial_account_request_dto.py
eis/accounting/model/create_financial_account_response_class.py
eis/accounting/model/create_number_range_request_dto.py
eis/accounting/model/create_number_range_response_class.py
eis/accounting/model/create_personal_account_request_dto.py
eis/accounting/model/create_personal_account_response_class.py
eis/accounting/model/financial_account_class.py
eis/accounting/model/financial_transaction_class.py
eis/accounting/model/financial_transaction_data_dto.py
eis/accounting/model/get_booking_entry_response_class.py
eis/accounting/model/get_financial_account_response_class.py
eis/accounting/model/get_financial_transaction_response_class.py
eis/accounting/model/get_number_range_response_class.py
eis/accounting/model/get_personal_account_response_class.py
eis/accounting/model/inline_response200.py
eis/accounting/model/inline_response503.py
eis/accounting/model/list_booking_entries_response_class.py
eis/accounting/model/list_financial_accounts_response_class.py
eis/accounting/model/list_financial_transactions_response_class.py
eis/accounting/model/list_number_range_response_class.py
eis/accounting/model/list_personal_accounts_response_class.py
eis/accounting/model/number_range_class.py
eis_accounting.egg-info/PKG-INFO
eis_accounting.egg-info/SOURCES.txt
eis_accounting.egg-info/dependency_links.txt
eis_accounting.egg-info/requires.txt
eis_accounting.egg-info/top_level.txt
