Metadata-Version: 2.1
Name: eis-accounting
Version: 1.24.0
Summary: EMIL AccountingService
Home-page: UNKNOWN
Author: Contact us
Author-email: kontakt@emil.de
License: UNKNOWN
Keywords: OpenAPI,OpenAPI-Generator,EMIL AccountingService
Platform: UNKNOWN
Requires-Python: >=3.6
